ament_flake8/__init__.py
ament_flake8/main.py
ament_flake8/pytest_marker.py
ament_flake8/configuration/ament_flake8.ini
ament_lint_flake8-0.14.4.data/data/share/ament_flake8/package.xml
ament_lint_flake8-0.14.4.data/data/share/ament_index/resource_index/packages/ament_flake8
ament_lint_flake8-0.14.4.dist-info/METADATA
ament_lint_flake8-0.14.4.dist-info/WHEEL
ament_lint_flake8-0.14.4.dist-info/entry_points.txt
ament_lint_flake8-0.14.4.dist-info/top_level.txt
ament_lint_flake8-0.14.4.dist-info/RECORD
