Metadata-Version: 2.1
Name: ament-lint-flake8
Version: 0.14.4
Summary: Check Python code style using flake8.
Home-page: https://github.com/ament/ament_lint
Download-URL: https://github.com/ament/ament_lint/releases
Author: D. Hood
Author-email: dhood@osrfoundation.org
Maintainer: Michael Jeronimo
Maintainer-email: michael.jeronimo@openrobotics.org
License: Apache License, Version 2.0
Keywords: ROS
Classifier: Intended Audience :: Developers
Classifier: License :: OSI Approved :: Apache Software License
Classifier: Programming Language :: Python
Classifier: Topic :: Software Development
Requires-Dist: setuptools
Requires-Dist: flake8 ==4.0.1
